<?xml version="1.0" encoding="utf-8" ?>
<programs>
	<program id="1">
		<programName>C</programName>
		<year>1972</year>
		<creator>Dennis MacAlistair Ritchie</creator>
	</program>

	<program id="2">
		<programName>javascript</programName>
		<year>1995</year>
		<creator>Brendan Eich</creator>
	</program>

	<program id="1">
		<programName>php</programName>
		<year>1995</year>
		<creator>Rasmus Lerdorf</creator>
	</program>

	<program id="3">
		<programName>java</programName>
		<year>1995</year>
		<creator>James Gosling</creator>
	</program>
</programs>
